{"ip_address": "202.152.77.212", "name": "mail1.bruneipress.com.bn.", "as_number": "10101", "as_org": "UNN", "country_code": "BN", "city": "", "version": "Microsoft DNS 6.1.7601 (1DB15D39)", "error": "Unexpected result for wikileaks.org: {[[141 105 65 113] [185 165 168 41] [195 35 109 53] [195 35 109 44]]}", "dnssec": "", "reliability": "0.00", "checked_at": "2021-08-31T17:11:46Z", "created_at": "2021-06-09T14:22:44Z"}
{"ip_address": "202.152.77.213", "name": "mail.bruneipress.com.bn.", "as_number": "10101", "as_org": "UNN", "country_code": "BN", "city": "Bandar Seri Begawan", "version": "", "error": "i/o timeout", "dnssec": "", "reliability": "0.00", "checked_at": "2023-03-05T07:13:39Z", "created_at": "2022-01-25T16:37:21Z"}
{"ip_address": "202.160.40.91", "name": "ftth.brunet.bn.", "as_number": "10094", "as_org": "Unified National Networks", "country_code": "BN", "city": "Kuala Belait", "version": "", "error": "", "dnssec": "false", "reliability": "1.00", "checked_at": "2022-08-24T02:52:45Z", "created_at": "2022-08-24T02:52:45Z"}
{"ip_address": "202.160.38.188", "name": "mail.ave.com.bn.", "as_number": "10094", "as_org": "Unified National Networks", "country_code": "BN", "city": "Bandar Seri Begawan", "version": "9.9.2-P2", "error": "", "dnssec": "false", "reliability": "1.00", "checked_at": "2022-08-24T02:52:48Z", "created_at": "2022-08-24T02:52:48Z"}
{"ip_address": "202.152.80.38", "name": "smp-80-38.simpur.net.bn.", "as_number": "10101", "as_org": "UNN", "country_code": "BN", "city": "Bandar Seri Begawan", "version": "", "error": "", "dnssec": "false", "reliability": "1.00", "checked_at": "2022-08-24T02:53:06Z", "created_at": "2022-08-24T02:53:06Z"}
{"ip_address": "61.6.225.234", "name": "234-225.adsl.static.espeed.com.bn.", "as_number": "10094", "as_org": "Unified National Networks", "country_code": "BN", "city": "Bandar Seri Begawan", "version": "dnsmasq-2.49", "error": "", "dnssec": "false", "reliability": "1.00", "checked_at": "2022-11-02T09:39:21Z", "created_at": "2022-10-27T21:59:46Z"}
{"ip_address": "61.6.225.205", "name": "205-225.adsl.static.espeed.com.bn.", "as_number": "10094", "as_org": "Unified National Networks", "country_code": "BN", "city": "Bandar Seri Begawan", "version": "", "error": "i/o timeout", "dnssec": "", "reliability": "0.07", "checked_at": "2023-02-27T23:59:41Z", "created_at": "2023-02-19T19:38:59Z"}
{"ip_address": "119.160.135.201", "name": "201-135.adsl.static.espeed.com.bn.", "as_number": "10094", "as_org": "Unified National Networks", "country_code": "BN", "city": "Bandar Seri Begawan", "version": "", "error": "i/o timeout", "dnssec": "", "reliability": "0.00", "checked_at": "2023-08-12T21:07:57Z", "created_at": "2023-03-18T22:38:54Z"}
